sgrna_designer/__init__.py
sgrna_designer/_nbdev.py
sgrna_designer/design.py
sgrna_designer/ensembl.py
sgrna_designer/tile.py
sgrna_designer-0.0.2.dist-info/LICENSE
sgrna_designer-0.0.2.dist-info/METADATA
sgrna_designer-0.0.2.dist-info/WHEEL
sgrna_designer-0.0.2.dist-info/entry_points.txt
sgrna_designer-0.0.2.dist-info/top_level.txt
sgrna_designer-0.0.2.dist-info/RECORD
