Metadata-Version: 2.1
Name: sgrna-designer
Version: 0.0.2
Summary: Python library to design sgRNA oligos
Home-page: https://github.com/gpp-rnd/sgrna_designer/tree/master/
Author: Peter DeWeirdt
Author-email: petedeweirdt@gmail.com
License: Apache Software License 2.0
Keywords: CRISPR,ensembl,python
Platform: UNKNOWN
Classifier: Development Status :: 3 - Alpha
Classifier: Intended Audience :: Developers
Classifier: Natural Language :: English
Classifier: Programming Language :: Python :: 3.6
Classifier: Programming Language :: Python :: 3.7
Classifier: Programming Language :: Python :: 3.8
Classifier: License :: OSI Approved :: Apache Software License
Requires-Python: >=3.6
Requires-Dist: pandas (>=1.0.0)
Requires-Dist: requests (>=2.25.0)
